Class Problem/Lab Day 01/HW-Problem/Nor-Implementation/NOR.v
module F_NOR(output F, input w, x, y, z);

    wire w_not, w1, w2, w3, w4, w5, w6;

    nor n1(w_not, w, w);
    nor n2(w1, w_not, x);
    nor n3(w2, w, z);
    nor n4(w3, y, z);

    nor n5(w4, w1, w2);
    nor n6(w5, w4, w4);
    nor n7(w6, w5, w3);

    nor n8(F, w6, w6);


endmodule

module test_NOR;

    wire F;
    reg w, x, y, z;
    F_NOR uut (F, w, x, y, z);

    initial begin
        $dumpfile("NOR.vcd");
        $dumpvars(0, test_NOR);

        w = 0; x = 0; y = 0; z = 0; #10;
        w = 0; x = 0; y = 0; z = 1; #10;
        w = 0; x = 0; y = 1; z = 0; #10;
        w = 0; x = 0; y = 1; z = 1; #10;
        w = 0; x = 1; y = 0; z = 0; #10;
        w = 0; x = 1; y = 0; z = 1; #10;
        w = 0; x = 1; y = 1; z = 0; #10;
        w = 0; x = 1; y = 1; z = 1; #10;
        w = 1; x = 0; y = 0; z = 0; #10;
        w = 1; x = 0; y = 0; z = 1; #10;
        w = 1; x = 0; y = 1; z = 0; #10;
        w = 1; x = 0; y = 1; z = 1; #10;
        w = 1; x = 1; y = 0; z = 0; #10;
        w = 1; x = 1; y = 0; z = 1; #10;
        w = 1; x = 1; y = 1; z = 0; #10;
        w = 1; x = 1; y = 1; z = 1; #10;
    end
    initial #200 $finish;

endmodule

Class Problem/Lab Day 01/HW-Problem/Nor-Implementation/NOR.vcd
$date
	Thu Sep 19 21:07:41 2024
$end
$version
	Icarus Verilog
$end
$timescale
	1s
$end
$scope module test_NOR $end
$var wire 1 ! F $end
$var reg 1 " w $end
$var reg 1 # x $end
$var reg 1 $ y $end
$var reg 1 % z $end
$scope module uut $end
$var wire 1 ! F $end
$var wire 1 " w $end
$var wire 1 & w1 $end
$var wire 1 ' w2 $end
$var wire 1 ( w3 $end
$var wire 1 ) w4 $end
$var wire 1 * w5 $end
$var wire 1 + w6 $end
$var wire 1 , w_not $end
$var wire 1 # x $end
$var wire 1 $ y $end
$var wire 1 % z $end
$upscope $end
$upscope $end
$enddefinitions $end
#0
$dumpvars
1,
0+
1*
0)
1(
1'
0&
0%
0$
0#
0"
1!
$end
#10
0!
1+
0*
1)
0'
0(
1%
#20
1!
0+
1*
0)
1'
0%
1$
#30
0!
1+
0*
1)
0'
1%
#40
1*
1!
0)
0+
1'
1(
0%
0$
1#
#50
0!
1+
0*
1)
0'
0(
1%
#60
1!
0+
1*
0)
1'
0%
1$
#70
0!
1+
0*
1)
0'
1%
#80
1!
1*
0+
0)
1(
1&
0,
0%
0$
0#
1"
#90
0(
1%
#100
0%
1$
#110
1%
#120
0*
1)
1(
0&
0%
0$
1#
#130
0!
1+
0(
1%
#140
0%
1$
#150
1%
