Class Problem/anis-sir/Register_Counters/RippleCounter/Ripple_Counter_4bit.sv
// Ripple counter (See Fig. 6.8 (b))
// `timescale 1ns / 100 ps
//`timescale 1ns / 1000ps
module Ripple_Counter_4bit (A3, A2, A1, A0, Count, Reset);
	output A3, A2, A1, A0;
	input Count, Reset;
	// Instantiate complementing fl ip-fl op
	 Comp_D_flip_flop F0 (A0, Count, Reset);
	 Comp_D_flip_flop F1 (A1, A0, Reset);
	 Comp_D_flip_flop F2 (A2, A1, Reset);
	 Comp_D_flip_flop F3 (A3, A2, Reset);
endmodule
// Complementing flip-flop with delay
// Input to D flip-flop = Q'
module Comp_D_flip_flop (Q, CLK, Reset);
	 output Q;
	 input CLK, Reset;
	 reg Q;
	 always @ ( negedge CLK, posedge Reset)
	 if (Reset) 
	 	Q <= 1'b0;
	 else
	 	//Q <= #2 ~Q; // intra-assignment delay 
	 	Q <= #2 ~Q;
endmodule

Class Problem/anis-sir/Register_Counters/RippleCounter/t_Ripple_Counter_4bit.sv
// Stimulus for testing ripple counter
`include "Ripple_Counter_4bit.sv"
module t_Ripple_Counter_4bit;
 	reg Count;
	reg Reset;
	//wire [3:0] A0, A1, A2, A3;
	wire [3:0] A;
		// Instantiate ripple counter
	Ripple_Counter_4bit M0 (A[3], A[2], A[1], A[0], Count, Reset); 
	//Ripple_Counter_4bit M0 (A3, A2, A1, A0, Count, Reset);
	initial 
		begin
			$dumpfile("t_Ripple_Counter_4bit.vcd");
			$dumpvars(0, t_Ripple_Counter_4bit);
		end 
	 initial #170 $finish;   
     initial
       begin
         Count = 1'b0;
         repeat(33)
   		    #5 Count = ~Count; 
   	   end
	initial
	 begin
	 	#4 Reset = 1'b0;
		#4 Reset = 1'b1;
        #4 Reset = 1'b0; 
        //#4 Reset = 1'b1;
	 end
	 always @ (posedge Count)
		 $monitor("Time = ",$time,"  Output =  %h ",A);
endmodule

Class Problem/anis-sir/Register_Counters/RippleCounter/t_Ripple_Counter_4bit.vcd
$date
	Tue Jul 09 13:26:47 2024
$end
$version
	Icarus Verilog
$end
$timescale
	1s
$end
$scope module t_Ripple_Counter_4bit $end
$var wire 4 ! A [3:0] $end
$var reg 1 " Count $end
$var reg 1 # Reset $end
$scope module M0 $end
$var wire 1 " Count $end
$var wire 1 # Reset $end
$var wire 1 $ A3 $end
$var wire 1 % A2 $end
$var wire 1 & A1 $end
$var wire 1 ' A0 $end
$scope module F0 $end
$var wire 1 " CLK $end
$var wire 1 # Reset $end
$var reg 1 ' Q $end
$upscope $end
$scope module F1 $end
$var wire 1 ' CLK $end
$var wire 1 # Reset $end
$var reg 1 & Q $end
$upscope $end
$scope module F2 $end
$var wire 1 & CLK $end
$var wire 1 # Reset $end
$var reg 1 % Q $end
$upscope $end
$scope module F3 $end
$var wire 1 % CLK $end
$var wire 1 # Reset $end
$var reg 1 $ Q $end
$upscope $end
$upscope $end
$upscope $end
$enddefinitions $end
$comment Show the parameter values. $end
$dumpall
$end
#0
$dumpvars
x'
x&
x%
x$
x#
0"
bx !
$end
#4
0#
#5
1"
#8
0'
0&
0%
b0 !
0$
1#
#10
0"
#12
0#
#15
1"
#20
0"
#22
b1 !
1'
#25
1"
#30
0"
#32
b0 !
0'
#34
b10 !
1&
#35
1"
#40
0"
#42
b11 !
1'
#45
1"
#50
0"
#52
b10 !
0'
#54
b0 !
0&
#55
1"
#56
b100 !
1%
#60
0"
#62
b101 !
1'
#65
1"
#70
0"
#72
b100 !
0'
#74
b110 !
1&
#75
1"
#80
0"
#82
b111 !
1'
#85
1"
#90
0"
#92
b110 !
0'
#94
b100 !
0&
#95
1"
#96
b0 !
0%
#98
b1000 !
1$
#100
0"
#102
b1001 !
1'
#105
1"
#110
0"
#112
b1000 !
0'
#114
b1010 !
1&
#115
1"
#120
0"
#122
b1011 !
1'
#125
1"
#130
0"
#132
b1010 !
0'
#134
b1000 !
0&
#135
1"
#136
b1100 !
1%
#140
0"
#142
b1101 !
1'
#145
1"
#150
0"
#152
b1100 !
0'
#154
b1110 !
1&
#155
1"
#160
0"
#162
b1111 !
1'
