Class Problem/LabTest4/LabTest.v
module Lab_Test6_Up (A2, A1, A0, Count, Reset);
    output A2, A1, A0;
    input Count, Reset;

    // Instantiate complementing D flip-flops for the up counter
    Comp_D_flip_flop F0 (A0, Count, Reset);
    Comp_D_flip_flop F1 (A1, A0, Reset);
    Comp_D_flip_flop F2 (A2, A1, Reset);
endmodule

module Lab_Test6_Down (A2, A1, A0, Count, Reset);
    output A2, A1, A0;
    input Count, Reset;

    // Instantiate regular D flip-flops for the down counter
    Down_D_flip_flop F0 (A0, Count, Reset);
    Down_D_flip_flop F1 (A1, A0, Reset);
    Down_D_flip_flop F2 (A2, A1, Reset);
endmodule

module Comp_D_flip_flop (Q, CLK, Reset);
    output reg Q;
    input CLK, Reset;

    always @(negedge CLK or posedge Reset) begin
        if (Reset) 
            Q <= 1'b0; 
        else 
            Q <= ~Q; 
    end
endmodule

module Down_D_flip_flop (Q, CLK, Reset);
    output reg Q;
    input CLK, Reset;

    always @(posedge CLK or posedge Reset) begin
        if (Reset) 
            Q <= 1'b0; 
        else 
            Q <= ~Q; 
    end
endmodule

module t_Lab_Test6;
 	reg CLK;
	reg Reset;
	wire [2:0] A;
	wire [2:0] B;
	
	 Lab_Test6_Up N (A[2], A[1], A[0], CLK, Reset);
	 Lab_Test6_Down P (B[2], B[1], B[0], CLK, Reset);  
	
	initial 
		begin
			$dumpfile("LabTest.vcd");
			$dumpvars(0, t_Lab_Test6);
		end 
	 initial #170 $finish;   
     initial
       begin
         CLK = 1'b0;
         repeat(33)
   		    #5 CLK = ~CLK; 
   	   end
	initial
	 begin
	 	#4 Reset = 1'b0;
		#4 Reset = 1'b1;
        #4 Reset = 1'b0; 
	 end
endmodule

Class Problem/LabTest4/t1.vcd
$date
	Wed Nov 20 15:29:47 2024
$end
$version
	Icarus Verilog
$end
$timescale
	1s
$end
$scope module t_Lab_Test6 $end
$var wire 3 ! B [2:0] $end
$var wire 3 " A [2:0] $end
$var reg 1 # CLK $end
$var reg 1 $ Reset $end
$scope module N $end
$var wire 1 # Count $end
$var wire 1 $ Reset $end
$var wire 1 % A2 $end
$var wire 1 & A1 $end
$var wire 1 ' A0 $end
$scope module F0 $end
$var wire 1 # CLK $end
$var wire 1 $ Reset $end
$var reg 1 ' Q $end
$upscope $end
$scope module F1 $end
$var wire 1 ' CLK $end
$var wire 1 $ Reset $end
$var reg 1 & Q $end
$upscope $end
$scope module F2 $end
$var wire 1 & CLK $end
$var wire 1 $ Reset $end
$var reg 1 % Q $end
$upscope $end
$upscope $end
$scope module P $end
$var wire 1 # Count $end
$var wire 1 $ Reset $end
$var wire 1 ( A2 $end
$var wire 1 ) A1 $end
$var wire 1 * A0 $end
$scope module F0 $end
$var wire 1 # CLK $end
$var wire 1 $ Reset $end
$var reg 1 * Q $end
$upscope $end
$scope module F1 $end
$var wire 1 * CLK $end
$var wire 1 $ Reset $end
$var reg 1 ) Q $end
$upscope $end
$scope module F2 $end
$var wire 1 ) CLK $end
$var wire 1 $ Reset $end
$var reg 1 ( Q $end
$upscope $end
$upscope $end
$upscope $end
$enddefinitions $end
#0
$dumpvars
x*
x)
x(
x'
x&
x%
0$
0#
bx "
bx !
$end
#4
0'
0&
b0 "
0%
0*
0)
b0 !
0(
1$
#5
1#
#8
0$
#10
b1 "
1'
0#
#15
1(
1)
b111 !
1*
1#
#20
1&
b10 "
0'
0#
#25
b110 !
0*
1#
#30
b11 "
1'
0#
#35
0)
b101 !
1*
1#
#40
1%
0&
b100 "
0'
0#
#45
b100 !
0*
1#
#50
b101 "
1'
0#
#55
0(
1)
b11 !
1*
1#
#60
1&
b110 "
0'
0#
#65
b10 !
0*
1#
#70
b111 "
1'
0#
#75
0)
b1 !
1*
1#
#80
0%
0&
b0 "
0'
0#
#85
b0 !
0*
1#
#90
b1 "
1'
0#
#95
1(
1)
b111 !
1*
1#
#100
1&
b10 "
0'
0#
#105
b110 !
0*
1#
#110
b11 "
1'
0#
#115
0)
b101 !
1*
1#
#120
1%
0&
b100 "
0'
0#
#125
b100 !
0*
1#
#130
b101 "
1'
0#
#135
0(
1)
b11 !
1*
1#
#140
1&
b110 "
0'
0#
#145
b10 !
0*
1#
#150
b111 "
1'
0#
#155
0)
b1 !
1*
1#
#160
0%
0&
b0 "
0'
0#
#165
b0 !
0*
1#
