Class Problem/anis-sir/Sequential/Practice/Moore/DFF.sv
// Gate-level description of circuit of Fig. 4.2 
// D fl ip-fl op with asynchronous reset (V2001, V2005)
module DFF ( output reg Q, input D, Clk, rst);
	always @( posedge Clk, negedge rst)
	 if (!rst) Q <= 1'b0; // Same as: if (rst == 0)
	else Q <= D;
endmodule

Class Problem/anis-sir/Sequential/Practice/Moore/TFF.sv
// T fl ip-fl op from D fl ip-fl op and gates
`include "DFF.sv"
module TFF (Q, T, Clk, rst);
 	output Q;
	input T, Clk, rst;
	wire DT;
	 
	 assign DT = Q ^ T ; // Continuous assignment
	 DFF TF1 (Q, DT, Clk, rst); 	// Instantiate the D fl ip-fl op
endmodule

Class Problem/anis-sir/Sequential/Practice/Moore/Moore5_20.v
`include "TFF.sv"

module Moore5_20(output y_out, A,B, input x_in, clk, res);

    wire TA, TB;

    assign TA = x_in & B;
    assign TB = x_in;
    assign y_out = A & B;

    TFF t1(A, TA, clk, res);
    TFF t2(B, TB, clk, res);

endmodule

module t_Moore5_20;
	wire t_y_out, A, B;
 	reg t_x_in, t_clock, t_reset;
	//Moore_Model_Fig_5_20 M1 (t_y_out_1, t_x_in, t_clock, t_reset);
	Moore5_20 M2 (t_y_out, A, B, t_x_in, t_clock, t_reset);
	initial 
		begin
		   $dumpfile("Moore5_20.vcd");
	       $dumpvars(0, t_Moore5_20);
		end
	initial #100 $finish;
	initial 
	  begin 
	  	  t_reset = 0;
	      t_clock = 0;
	      #5 t_reset = 1;
	      repeat (16)
	        #5 t_clock = ~t_clock; 
      end
	initial 
	 begin
 		t_x_in = 0;
		#15 t_x_in = 1;
		repeat (8)
		   #10 t_x_in = ~t_x_in;
	end
endmodule

Class Problem/anis-sir/Sequential/Practice/Moore/Moore5_20.vcd
$date
	Tue Nov 12 23:38:59 2024
$end
$version
	Icarus Verilog
$end
$timescale
	1s
$end
$scope module t_Moore5_20 $end
$var wire 1 ! t_y_out $end
$var wire 1 " B $end
$var wire 1 # A $end
$var reg 1 $ t_clock $end
$var reg 1 % t_reset $end
$var reg 1 & t_x_in $end
$scope module M2 $end
$var wire 1 ' TA $end
$var wire 1 ( TB $end
$var wire 1 $ clk $end
$var wire 1 % res $end
$var wire 1 & x_in $end
$var wire 1 ! y_out $end
$var wire 1 " B $end
$var wire 1 # A $end
$scope module t1 $end
$var wire 1 $ Clk $end
$var wire 1 ) DT $end
$var wire 1 ' T $end
$var wire 1 % rst $end
$var wire 1 # Q $end
$scope module TF1 $end
$var wire 1 $ Clk $end
$var wire 1 ) D $end
$var wire 1 % rst $end
$var reg 1 # Q $end
$upscope $end
$upscope $end
$scope module t2 $end
$var wire 1 $ Clk $end
$var wire 1 * DT $end
$var wire 1 ( T $end
$var wire 1 % rst $end
$var wire 1 " Q $end
$scope module TF1 $end
$var wire 1 $ Clk $end
$var wire 1 * D $end
$var wire 1 % rst $end
$var reg 1 " Q $end
$upscope $end
$upscope $end
$upscope $end
$upscope $end
$enddefinitions $end
#0
$dumpvars
0*
0)
0(
0'
0&
0%
0$
0#
0"
0!
$end
#5
1%
#10
1$
#15
1*
0$
1(
1&
#20
1)
0*
1'
1"
1$
#25
0)
0'
1*
0$
0(
0&
#30
1$
#35
1)
1'
0*
0$
1(
1&
#40
1*
0'
1#
0"
1$
#45
0*
0$
0(
0&
#50
1$
#55
1*
0$
1(
1&
#60
0)
0*
1!
1'
1"
1$
#65
1)
0'
1*
0$
0(
0&
#70
1$
#75
0)
1'
0*
0$
1(
1&
#80
1*
0!
0'
0#
0"
1$
#85
0*
0$
0(
0&
#95
1*
1(
1&
