Class Problem/anis-sir/Sequential/Practice/Moore/DFF.sv
// Gate-level description of circuit of Fig. 4.2 
// D fl ip-fl op with asynchronous reset (V2001, V2005)
module DFF ( output reg Q, input D, Clk, rst);
	always @( posedge Clk, negedge rst)
	 if (!rst) Q <= 1'b0; // Same as: if (rst == 0)
	else Q <= D;
endmodule

Class Problem/anis-sir/Sequential/Practice/Moore/TFF.sv
// T fl ip-fl op from D fl ip-fl op and gates
`include "DFF.sv"
module TFF (Q, T, Clk, rst);
 	output Q;
	input T, Clk, rst;
	wire DT;
	 
	 assign DT = Q ^ T ; // Continuous assignment
	 DFF TF1 (Q, DT, Clk, rst); 	// Instantiate the D fl ip-fl op
endmodule

Class Problem/anis-sir/Sequential/Practice/Moore/Moore5_19.v
`include "TFF.sv"

module Moore5_19 (output y_out, A, B, input x_in, clk, res);

    wire Ta, Tb;

    // State transition logic for T flip-flops
    assign Ta = ~x_in & B;
    assign Tb = (~x_in & ~B) | (~x_in & A) | (x_in & ~A & B);
    assign y_out=x_in;

    // T flip-flops for state bits A and B
    TFF t11(A, Ta, clk, res);
    TFF t22(B, Tb, clk, res);

endmodule

module t_Moore5_19;
    wire A, B, y_out;
    reg t_x_in, t_clock, t_reset;

    // Module instantiation with corrected port mapping
    Moore5_19 MM (y_out, A, B, t_x_in, t_clock, t_reset);

    initial begin
        $dumpfile("Moore5_19.vcd");
        $dumpvars(0, t_Moore5_19);
    end

    initial #200 $finish;
	initial begin t_clock = 0; forever #5 t_clock = ~t_clock; end
	initial fork    
	 t_reset = 0;
	 #2 t_reset = 1;
	 #87 t_reset = 0;
	 #89 t_reset = 1;
	 
	 #10 t_x_in = 1;
	 #30 t_x_in = 0;
	 #40 t_x_in = 1;
	 #50 t_x_in = 0;
	 #52 t_x_in = 1;
	 #54 t_x_in = 0;
	 #70 t_x_in = 1;
	 #80 t_x_in = 1;
	 #70 t_x_in = 0;
	 #90 t_x_in = 1;
	 #100 t_x_in = 0;
	 #120 t_x_in = 1;
	 #160 t_x_in = 0;
	 #170 t_x_in = 1;
   join
endmodule

Class Problem/anis-sir/Sequential/Practice/Moore/Moore5_19.vcd
$date
	Wed Nov 13 00:06:21 2024
$end
$version
	Icarus Verilog
$end
$timescale
	1s
$end
$scope module t_Moore5_19 $end
$var wire 1 ! y_out $end
$var wire 1 " B $end
$var wire 1 # A $end
$var reg 1 $ t_clock $end
$var reg 1 % t_reset $end
$var reg 1 & t_x_in $end
$scope module MM $end
$var wire 1 ' Ta $end
$var wire 1 ( Tb $end
$var wire 1 $ clk $end
$var wire 1 % res $end
$var wire 1 & x_in $end
$var wire 1 ! y_out $end
$var wire 1 " B $end
$var wire 1 # A $end
$scope module t11 $end
$var wire 1 $ Clk $end
$var wire 1 ) DT $end
$var wire 1 ' T $end
$var wire 1 % rst $end
$var wire 1 # Q $end
$scope module TF1 $end
$var wire 1 $ Clk $end
$var wire 1 ) D $end
$var wire 1 % rst $end
$var reg 1 # Q $end
$upscope $end
$upscope $end
$scope module t22 $end
$var wire 1 $ Clk $end
$var wire 1 * DT $end
$var wire 1 ( T $end
$var wire 1 % rst $end
$var wire 1 " Q $end
$scope module TF1 $end
$var wire 1 $ Clk $end
$var wire 1 * D $end
$var wire 1 % rst $end
$var reg 1 " Q $end
$upscope $end
$upscope $end
$upscope $end
$upscope $end
$enddefinitions $end
#0
$dumpvars
x*
0)
x(
0'
x&
0%
0$
0#
0"
x!
$end
#2
1%
#5
x)
x'
x"
1$
#10
0)
0'
0$
1!
1&
#15
1$
#20
0$
#25
1$
#30
x)
x(
x'
0$
0!
0&
#35
x#
1$
#40
0'
0$
1!
1&
#45
1$
#50
x(
x'
0$
0!
0&
#52
0'
1!
1&
#54
x(
x'
0!
0&
#55
1$
#60
0$
#65
1$
#70
0'
0$
1!
1&
#75
1$
#80
0$
#85
1$
#87
0*
0(
0)
0#
0"
0%
#89
1%
#90
0$
#95
1$
#100
1*
1(
0$
0!
0&
#105
0(
1)
1*
1'
1"
1$
#110
0$
#115
0*
1(
0)
1#
1$
#120
1*
0(
1)
0'
0$
1!
1&
#125
1$
#130
0$
#135
1$
#140
0$
#145
1$
#150
0$
#155
1$
#160
0*
1(
0)
1'
0$
0!
0&
#165
1*
0'
0#
0"
1$
#170
0*
0(
0$
1!
1&
