Class Problem/anis-sir/Sequential/JK/JK_FF.sv
// Functional description of JK fl ip-fl op (V2001, 2005)
module JK_FF ( input J, K, Clk, output reg Q, output Q_b);
assign Q_b = ~ Q ;
always @ ( posedge Clk)
case ({J,K})
 2'b00: Q <= Q;
 2'b01: Q <= 1'b0;
 2'b10: Q <= 1'b1;
 2'b11: Q <= !Q;
endcase
endmodule

Class Problem/anis-sir/Sequential/JK/t_JK_FF.sv
`include "JK_FF.sv"
module t_JK_FF;
	wire t_Q, t_Q_b;
	reg t_J,t_K, t_Clk;
	JK_FF  JK ( t_J,t_K, t_Clk, t_Q, t_Q_b );
	initial 
		begin
		   $dumpfile("t_JK_FF.vcd");
	       $dumpvars(0, t_JK_FF);
		end
	initial #110 $finish;
	initial begin t_Clk = 0; forever #5 t_Clk = ~t_Clk; end
	initial fork
	     		 
		 #2 t_J = 1;
		 #2 t_K = 0;
		 
		 #22 t_J = 0;
		 #22 t_K = 1;
		 
		 //#32 t_J = 0;
		 #32 t_K = 0;  
		 
		 #42 t_J = 1;
		 #42 t_K = 1;
		 
		 
		 #52 t_J = 0;
		 #52 t_K = 0; 
		 
		 #62 t_J = 1;
		 #62 t_K = 1;	 
	 join
endmodule

Class Problem/anis-sir/Sequential/JK/t_JK_FF.vcd
$date
	Sun Jul 07 15:20:42 2024
$end
$version
	Icarus Verilog
$end
$timescale
	1s
$end
$scope module t_JK_FF $end
$var wire 1 ! t_Q_b $end
$var wire 1 " t_Q $end
$var reg 1 # t_Clk $end
$var reg 1 $ t_J $end
$var reg 1 % t_K $end
$scope module JK $end
$var wire 1 # Clk $end
$var wire 1 $ J $end
$var wire 1 % K $end
$var wire 1 ! Q_b $end
$var reg 1 " Q $end
$upscope $end
$upscope $end
$enddefinitions $end
$comment Show the parameter values. $end
$dumpall
$end
#0
$dumpvars
x%
x$
0#
x"
x!
$end
#2
1$
0%
#5
0!
1"
1#
#10
0#
#15
1#
#20
0#
#22
0$
1%
#25
1!
0"
1#
#30
0#
#32
0%
#35
1#
#40
0#
#42
1$
1%
#45
0!
1"
1#
#50
0#
#52
0$
0%
#55
1#
#60
0#
#62
1$
1%
#65
1!
0"
1#
#70
0#
#75
0!
1"
1#
#80
0#
#85
1!
0"
1#
#90
0#
#95
0!
1"
1#
#100
0#
#105
1!
0"
1#
