Class Problem/anis-sir/Lecture6/slide14.sv
module slide14_beh(input A,B,C,D, output w,x,y,z);
	assign z = ~D;
	assign y = (C&D)|(~C&~D);
	assign x = (~B&C)|(~B&D)|(B&(~C)&(~D));
	assign w = A|(B&C)|(B&D);
endmodule       


module t_slide14_beh;
	reg A,B,C,D;
	wire w,x,y,z;
	slide14_beh Inst1 (A,B,C,D,w,x,y,z);
	initial  #200 $finish;
	initial
	begin : initialize
	  $dumpfile("t_slide14_beh.vcd");
	  $dumpvars(0,t_slide14_beh);
	      A=1'b0; B=1'b0; C=1'b0; D=1'b0;
	  #10 A=1'b0; B=1'b0; C=1'b0; D=1'b1;
	  #10 A=1'b0; B=1'b0; C=1'b1; D=1'b0; 
	  #10 A=1'b0; B=1'b0; C=1'b1; D=1'b1;
	  #10 A=1'b0; B=1'b1; C=1'b0; D=1'b0;
	  #10 A=1'b0; B=1'b1; C=1'b0; D=1'b1;
	  #10 A=1'b0; B=1'b1; C=1'b1; D=1'b0; 
	  #10 A=1'b0; B=1'b1; C=1'b1; D=1'b1;
	  #10 A=1'b1; B=1'b0; C=1'b0; D=1'b0;
	  #10 A=1'b1; B=1'b0; C=1'b0; D=1'b1;
	  #10 A=1'b1; B=1'b0; C=1'b1; D=1'b0; 
	  #10 A=1'b1; B=1'b0; C=1'b1; D=1'b1;
	  #10 A=1'b1; B=1'b1; C=1'b0; D=1'b0;
	  #10 A=1'b1; B=1'b1; C=1'b0; D=1'b1;
	  #10 A=1'b1; B=1'b1; C=1'b1; D=1'b0; 
	  #10 A=1'b1; B=1'b1; C=1'b1; D=1'b1;
	end  // initialize
	
	initial
	  $monitor("Time=",$time," A=%b B=%b C=%b D=%b w=%b x=%b y=%b z=%b",A,B,C,D,w,x,y,z); 
endmodule

Class Problem/anis-sir/Lecture6/t_slide14_beh.vcd
$date
	Mon Sep 23 13:07:28 2024
$end
$version
	Icarus Verilog
$end
$timescale
	1s
$end
$scope module t_slide14_beh $end
$var wire 1 ! z $end
$var wire 1 " y $end
$var wire 1 # x $end
$var wire 1 $ w $end
$var reg 1 % A $end
$var reg 1 & B $end
$var reg 1 ' C $end
$var reg 1 ( D $end
$scope module Inst1 $end
$var wire 1 % A $end
$var wire 1 & B $end
$var wire 1 ' C $end
$var wire 1 ( D $end
$var wire 1 $ w $end
$var wire 1 # x $end
$var wire 1 " y $end
$var wire 1 ! z $end
$upscope $end
$scope begin initialize $end
$upscope $end
$upscope $end
$enddefinitions $end
$comment Show the parameter values. $end
$dumpall
$end
#0
$dumpvars
0(
0'
0&
0%
0$
0#
1"
1!
$end
#10
0"
1#
0!
1(
#20
1!
0(
1'
#30
1"
0!
1(
#40
1!
0(
0'
1&
#50
0"
0#
1$
0!
1(
#60
1!
0(
1'
#70
1"
0!
1(
#80
1!
0(
0'
0&
1%
#90
0"
1#
0!
1(
#100
1!
0(
1'
#110
1"
0!
1(
#120
1!
0(
0'
1&
#130
0"
0#
0!
1(
#140
1!
0(
1'
#150
1"
0!
1(
