Class Problem/Lab Day 01/HW-Problem/Problem1_a.v
module F_NOR (
    output F,
    input w, x, y, z);

    wire w_not, w2, w3, w4, w5;
    nor G1(w_not, w, w);
    nor G2(w2, w_not, x);
    nor G3(w3, y, z);
    nor G4(w4, w, z);

    nor G5(w5, w2, w3, w4);
    nor G6(F, w5, w5);

endmodule

module Problem1_a;
    wire F;
    reg w, x, y, z;

    F_NOR FN (F, w, x, y, z);

    initial
    begin
        $dumpfile("Problem1_a");
        $dumpvars(0, Problem1_a);

        w = 1'b0; x = 1'b0; y = 1'b0; z = 1'b0;
        #10 w = 1'b0; x = 1'b0; y = 1'b0; z = 1'b1;
        #10 w = 1'b0; x = 1'b0; y = 1'b1; z = 1'b0;
        #10 w = 1'b0; x = 1'b0; y = 1'b1; z = 1'b1;
        #10 w = 1'b0; x = 1'b1; y = 1'b0; z = 1'b0;
        #10 w = 1'b0; x = 1'b1; y = 1'b0; z = 1'b1;
        #10 w = 1'b0; x = 1'b1; y = 1'b1; z = 1'b0;
        #10 w = 1'b0; x = 1'b1; y = 1'b1; z = 1'b1;
        #10 w = 1'b1; x = 1'b0; y = 1'b0; z = 1'b0;
        #10 w = 1'b1; x = 1'b0; y = 1'b0; z = 1'b1;
        #10 w = 1'b1; x = 1'b0; y = 1'b1; z = 1'b0;
        #10 w = 1'b1; x = 1'b0; y = 1'b1; z = 1'b1;
        #10 w = 1'b1; x = 1'b1; y = 1'b0; z = 1'b0;
        #10 w = 1'b1; x = 1'b1; y = 1'b0; z = 1'b1;
        #10 w = 1'b1; x = 1'b1; y = 1'b1; z = 1'b0;
        #10 w = 1'b1; x = 1'b1; y = 1'b1; z = 1'b1;

    end
    initial #160 $finish;

endmodule

Class Problem/Lab Day 01/HW-Problem/Problem1_a.vcd
$date
	Sun Sep 22 21:49:58 2024
$end
$version
	Icarus Verilog
$end
$timescale
	1s
$end
$scope module Problem1_a $end
$var wire 1 ! F $end
$var reg 1 " w $end
$var reg 1 # x $end
$var reg 1 $ y $end
$var reg 1 % z $end
$scope module FN $end
$var wire 1 ! F $end
$var wire 1 " w $end
$var wire 1 & w2 $end
$var wire 1 ' w3 $end
$var wire 1 ( w4 $end
$var wire 1 ) w5 $end
$var wire 1 * w_not $end
$var wire 1 # x $end
$var wire 1 $ y $end
$var wire 1 % z $end
$upscope $end
$upscope $end
$enddefinitions $end
#0
$dumpvars
1*
0)
1(
1'
0&
0%
0$
0#
0"
1!
$end
#10
0!
1)
0'
0(
1%
#20
1!
0)
1(
0%
1$
#30
0!
1)
0(
1%
#40
1!
0)
1(
1'
0%
0$
1#
#50
0!
1)
0'
0(
1%
#60
1!
0)
1(
0%
1$
#70
0!
1)
0(
1%
#80
1!
0)
1'
1&
0*
0%
0$
0#
1"
#90
0'
1%
#100
0%
1$
#110
1%
#120
1'
0&
0%
0$
1#
#130
0!
1)
0'
1%
#140
0%
1$
#150
1%
