Class Problem/Lab Day 01/HW-Problem/Problem1_b.v
module F_NAND (
    output F,
    input w, x, y, z);

    wire w_not, x_not, y_not, z_not;
    nand G1(w_not, w, w);
    nand G2(x_not, x, x);
    nand g3(y_not, y, y);
    nand g4(z_not, z, z);

    wire w5, w6, w7;
    nand G5(w5, w, x_not);
    nand G6(w6, y_not, z_not);
    nand G7(w7, w_not, z_not);

    nand G8(F, w5, w6, w7);
    
endmodule

module Problem1_b;
    wire F;
    reg w, x, y, z;

    F_NAND FN (F, w, x, y, z);

    initial
    begin
        $dumpfile("Problem1_b");
        $dumpvars(0, Problem1_b);

        w = 1'b0; x = 1'b0; y = 1'b0; z = 1'b0;
        #10 w = 1'b0; x = 1'b0; y = 1'b0; z = 1'b1;
        #10 w = 1'b0; x = 1'b0; y = 1'b1; z = 1'b0;
        #10 w = 1'b0; x = 1'b0; y = 1'b1; z = 1'b1;
        #10 w = 1'b0; x = 1'b1; y = 1'b0; z = 1'b0;
        #10 w = 1'b0; x = 1'b1; y = 1'b0; z = 1'b1;
        #10 w = 1'b0; x = 1'b1; y = 1'b1; z = 1'b0;
        #10 w = 1'b0; x = 1'b1; y = 1'b1; z = 1'b1;
        #10 w = 1'b1; x = 1'b0; y = 1'b0; z = 1'b0;
        #10 w = 1'b1; x = 1'b0; y = 1'b0; z = 1'b1;
        #10 w = 1'b1; x = 1'b0; y = 1'b1; z = 1'b0;
        #10 w = 1'b1; x = 1'b0; y = 1'b1; z = 1'b1;
        #10 w = 1'b1; x = 1'b1; y = 1'b0; z = 1'b0;
        #10 w = 1'b1; x = 1'b1; y = 1'b0; z = 1'b1;
        #10 w = 1'b1; x = 1'b1; y = 1'b1; z = 1'b0;
        #10 w = 1'b1; x = 1'b1; y = 1'b1; z = 1'b1;

    end
    initial #160 $finish;

endmodule

Class Problem/Lab Day 01/HW-Problem/Problem1_b.vcd
$date
	Sun Sep 22 21:50:23 2024
$end
$version
	Icarus Verilog
$end
$timescale
	1s
$end
$scope module Problem1_b $end
$var wire 1 ! F $end
$var reg 1 " w $end
$var reg 1 # x $end
$var reg 1 $ y $end
$var reg 1 % z $end
$scope module FN $end
$var wire 1 ! F $end
$var wire 1 " w $end
$var wire 1 & w5 $end
$var wire 1 ' w6 $end
$var wire 1 ( w7 $end
$var wire 1 ) w_not $end
$var wire 1 # x $end
$var wire 1 * x_not $end
$var wire 1 $ y $end
$var wire 1 + y_not $end
$var wire 1 % z $end
$var wire 1 , z_not $end
$upscope $end
$upscope $end
$enddefinitions $end
#0
$dumpvars
1,
1+
1*
1)
0(
0'
1&
0%
0$
0#
0"
1!
$end
#10
0!
1'
1(
0,
1%
#20
1!
0(
1,
0+
0%
1$
#30
0!
1(
0,
1%
#40
1!
0(
0'
1,
1+
0*
0%
0$
1#
#50
0!
1'
1(
0,
1%
#60
1!
0(
1,
0+
0%
1$
#70
0!
1(
0,
1%
#80
1!
0'
0&
1,
1+
1*
0)
0%
0$
0#
1"
#90
1'
0,
1%
#100
1,
0+
0%
1$
#110
0,
1%
#120
0'
1&
1,
1+
0*
0%
0$
1#
#130
0!
1'
0,
1%
#140
1,
0+
0%
1$
#150
0,
1%
