Class Problem/anis-sir/Register_Counters/BinaraCounter/BC4PL.v
// Four-bit binary counter with parallel load (V2001, 2005)
// See Figure 6.14and Table 6.6 
module Binary_Counter_4_Par_Load (
 output reg [3:0] A_count, // Data output
 output C_out, // Output carry
 input [3:0] Data_in, // Data input
 input Count, // Active high to count
 Load, // Active high to load
 CLK, // Positive-edge sensitive
 Clear_b // Active low
);
assign C_out = Count && (~Load) && (A_count == 4'b1111);
always @ ( posedge CLK, negedge Clear_b)
 if (~Clear_b) A_count <= 4'b0000;
 else if (Load) A_count <= Data_in;
 else if (Count) A_count <= A_count + 1'b1;
 else A_count <= A_count; // redundant statement
endmodule

module t_Binary_Counter_4_Par_Load;
	wire [3:0] A_count;
	wire C_out;
	reg [3:0] Data_in;
 	reg Count, Load, CLK, Clear_b;
	Binary_Counter_4_Par_Load BC4PL (A_count, C_out, Data_in, Count, Load, CLK, Clear_b);
	initial 
		begin
		   $dumpfile("BC4PL.vcd");
	       $dumpvars(0, t_Binary_Counter_4_Par_Load);
		end
	initial #150 $finish;
	initial 
	  begin 
	  	  Clear_b = 1;
	      CLK = 0;
	      #5 Clear_b = 0;
	      #7 Clear_b = 1;
	      repeat (25)
	        #5 CLK = ~CLK; 
      end
	initial 
	 begin
 		Load = 0;
	    Data_in =  4'b1010;
		#10 Load = 1;
		#12 Load = 0;
		#2 Count = 1;
		#12 Clear_b =0;
		#22 Clear_b =1;
	 end
endmodule

Class Problem/anis-sir/Register_Counters/BinaraCounter/BC4PL.vcd
$date
	Tue Nov 19 18:29:30 2024
$end
$version
	Icarus Verilog
$end
$timescale
	1s
$end
$scope module t_Binary_Counter_4_Par_Load $end
$var wire 1 ! C_out $end
$var wire 4 " A_count [3:0] $end
$var reg 1 # CLK $end
$var reg 1 $ Clear_b $end
$var reg 1 % Count $end
$var reg 4 & Data_in [3:0] $end
$var reg 1 ' Load $end
$scope module BC4PL $end
$var wire 1 # CLK $end
$var wire 1 ! C_out $end
$var wire 1 $ Clear_b $end
$var wire 1 % Count $end
$var wire 4 ( Data_in [3:0] $end
$var wire 1 ' Load $end
$var reg 4 ) A_count [3:0] $end
$upscope $end
$upscope $end
$enddefinitions $end
#0
$dumpvars
bx )
b1010 (
0'
b1010 &
x%
1$
0#
bx "
x!
$end
#5
0!
b0 "
b0 )
0$
#10
1'
#12
1$
#17
b1010 "
b1010 )
1#
#22
0#
0'
#24
1%
#27
b1011 "
b1011 )
1#
#32
0#
#36
b0 "
b0 )
0$
#37
1#
#42
0#
#47
1#
#52
0#
#57
1#
#58
1$
#62
0#
#67
b1 "
b1 )
1#
#72
0#
#77
b10 "
b10 )
1#
#82
0#
#87
b11 "
b11 )
1#
#92
0#
#97
b100 "
b100 )
1#
#102
0#
#107
b101 "
b101 )
1#
#112
0#
#117
b110 "
b110 )
1#
#122
0#
#127
b111 "
b111 )
1#
#132
0#
#137
b1000 "
b1000 )
1#
