Class Problem/temp/output.v
module half_adder_mod(input X, Y, output Sum_out, Carry_out);

    xor (Sum_out, X, Y);
    and (Carry_out, X, Y);

endmodule


module full_adder_mod(input X, Y, Cin, output Sum_out, Carry_out);

    wire Carry1, X_xor_Y, Carry2;
    half_adder_mod ha1(X, Y, X_xor_Y, Carry1);
    half_adder_mod ha2(X_xor_Y, Cin, Sum_out, Carry2);

    or (Carry_out, Carry1, Carry2);

endmodule


module three_bit_add_sub_mod(a, b, m, Sum_out, Carry_out);

    input [2:0]a, b;
    input m;
    output [2:0]Sum_out;
    output Carry_out;

    wire [2:0]b_xor_m, carry_wire;

    xor bx1(b_xor_m[0], b[0], m);
    xor bx2(b_xor_m[1], b[1], m);
    xor bx3(b_xor_m[2], b[2], m);

    full_adder_mod fa1(a[0], b_xor_m[0], m, Sum_out[0], carry_wire[0]);
    full_adder_mod fa2(a[1], b_xor_m[1], carry_wire[0], Sum_out[1], carry_wire[1]);
    full_adder_mod fa3(a[2], b_xor_m[2], carry_wire[1], Sum_out[2], Carry_out);

endmodule


module test_three_bit_add_sub_mod;

    reg [2:0]A_in, B_in;
    reg m;
    wire [2:0]Sum_out;
    wire Carry_out;

    three_bit_add_sub_mod add_sub_inst(A_in, B_in, m, Sum_out, Carry_out);

    initial begin
        $dumpfile("output.vcd");
        $dumpvars(0, test_three_bit_add_sub_mod);

        A_in = 3'b101; B_in = 3'b011; m = 1'b0; #10;  
        A_in = 3'b101; B_in = 3'b011; m = 1'b1; #10;  
        A_in = 3'b011; B_in = 3'b101; m = 1'b1; #10;    

        A_in = 3'b111; B_in = 3'b000; m = 1'b0; #10;    
        A_in = 3'b111; B_in = 3'b000; m = 1'b1; #10;   
        A_in = 3'b000; B_in = 3'b111; m = 1'b1; #10;    

        A_in = 3'b101; B_in = 3'b101; m = 1'b0; #10;  
        A_in = 3'b101; B_in = 3'b101; m = 1'b1; #10;    

        $finish;

    end

    initial begin
        
        $monitor("| A_in = %b, B_in = %b , m = %b | Carry_out = %b, Sum_out = %b |", A_in, B_in, m, Carry_out, Sum_out);

    end

endmodule

Class Problem/temp/output.vcd
$date
	Tue Oct 01 22:14:15 2024
$end
$version
	Icarus Verilog
$end
$timescale
	1s
$end
$scope module test_three_bit_add_sub_mod $end
$var wire 3 ! Sum_out [2:0] $end
$var wire 1 " Carry_out $end
$var reg 3 # A_in [2:0] $end
$var reg 3 $ B_in [2:0] $end
$var reg 1 % m $end
$scope module add_sub_inst $end
$var wire 3 & a [2:0] $end
$var wire 3 ' b [2:0] $end
$var wire 1 % m $end
$var wire 3 ( carry_wire [2:0] $end
$var wire 3 ) b_xor_m [2:0] $end
$var wire 3 * Sum_out [2:0] $end
$var wire 1 " Carry_out $end
$scope module fa1 $end
$var wire 1 + Carry_out $end
$var wire 1 % Cin $end
$var wire 1 , X $end
$var wire 1 - Y $end
$var wire 1 . X_xor_Y $end
$var wire 1 / Sum_out $end
$var wire 1 0 Carry2 $end
$var wire 1 1 Carry1 $end
$scope module ha1 $end
$var wire 1 1 Carry_out $end
$var wire 1 . Sum_out $end
$var wire 1 , X $end
$var wire 1 - Y $end
$upscope $end
$scope module ha2 $end
$var wire 1 0 Carry_out $end
$var wire 1 / Sum_out $end
$var wire 1 . X $end
$var wire 1 % Y $end
$upscope $end
$upscope $end
$scope module fa2 $end
$var wire 1 2 Carry_out $end
$var wire 1 3 Cin $end
$var wire 1 4 X $end
$var wire 1 5 Y $end
$var wire 1 6 X_xor_Y $end
$var wire 1 7 Sum_out $end
$var wire 1 8 Carry2 $end
$var wire 1 9 Carry1 $end
$scope module ha1 $end
$var wire 1 9 Carry_out $end
$var wire 1 6 Sum_out $end
$var wire 1 4 X $end
$var wire 1 5 Y $end
$upscope $end
$scope module ha2 $end
$var wire 1 8 Carry_out $end
$var wire 1 7 Sum_out $end
$var wire 1 6 X $end
$var wire 1 3 Y $end
$upscope $end
$upscope $end
$scope module fa3 $end
$var wire 1 " Carry_out $end
$var wire 1 : Cin $end
$var wire 1 ; X $end
$var wire 1 < Y $end
$var wire 1 = X_xor_Y $end
$var wire 1 > Sum_out $end
$var wire 1 ? Carry2 $end
$var wire 1 @ Carry1 $end
$scope module ha1 $end
$var wire 1 @ Carry_out $end
$var wire 1 = Sum_out $end
$var wire 1 ; X $end
$var wire 1 < Y $end
$upscope $end
$scope module ha2 $end
$var wire 1 ? Carry_out $end
$var wire 1 > Sum_out $end
$var wire 1 = X $end
$var wire 1 : Y $end
$upscope $end
$upscope $end
$upscope $end
$upscope $end
$enddefinitions $end
#0
$dumpvars
0@
1?
0>
1=
0<
1;
1:
09
18
07
16
15
04
13
12
11
00
0/
0.
1-
1,
1+
b0 *
b11 )
bz11 (
b11 '
b101 &
0%
b11 $
b101 #
1"
b0 !
$end
#10
0:
13
02
10
bz01 (
1+
17
08
0>
0?
1.
01
06
0=
1@
0-
05
1<
b100 )
b10 !
b10 *
0/
1%
#20
1:
19
bz11 (
12
15
0<
17
08
b110 !
b110 *
1>
0"
b10 )
06
0=
0@
14
0;
b101 $
b101 '
b11 #
b11 &
#30
0:
02
0"
16
09
03
1>
0?
05
bz00 (
0+
1=
b0 )
b111 !
b111 *
1/
00
1;
0%
b0 $
b0 '
b111 #
b111 &
#40
1:
12
1>
1"
0.
11
06
19
0=
1@
13
1-
15
1<
bz11 (
1+
b111 )
b111 !
b111 *
1/
00
1%
#50
03
0:
0-
05
0<
1/
00
0+
07
08
bz00 (
02
b1 !
b1 *
0>
0?
0"
b0 )
0.
01
06
09
0=
0@
0,
04
0;
b111 $
b111 '
b0 #
b0 &
#60
17
13
bz01 (
1+
1"
11
1@
0>
1-
1<
0.
0=
b101 )
b10 !
b10 *
0/
1,
1;
0%
b101 $
b101 '
b101 #
b101 &
#70
1?
1:
13
12
10
bz11 (
1+
07
18
0>
1"
1.
01
16
1=
0@
0-
15
0<
b10 )
b0 !
b0 *
0/
1%
