Class Problem/Lab Day 01/HW-Problem/Nand-Implementation/NAND.v
module F_NAND(output F, input w, x, y, z);

    wire w_not, x_not, y_not, z_not, w1, w2, w3, w4, w5;

    nand n1(w_not, w, w);
    nand n2(x_not, x, x);
    nand n3(y_not, y, y);
    nand n4(z_not, z, z);

    nand n5(w1, w, x_not);
    nand n6(w2, w_not, z_not);
    nand n7(w3, y_not, z_not);

    nand n8(w4, w1, w2);
    nand n9(w5, w4, w4);
    nand n10(F, w3, w5);

endmodule

module test_NAND;

    wire F;
    reg w, x, y, z;
    F_NAND uut (F, w, x, y, z);

    initial begin
        $dumpfile("NAND.vcd");
        $dumpvars(0, test_NAND);

        w = 0; x = 0; y = 0; z = 0; #10;
        w = 0; x = 0; y = 0; z = 1; #10;
        w = 0; x = 0; y = 1; z = 0; #10;
        w = 0; x = 0; y = 1; z = 1; #10;
        w = 0; x = 1; y = 0; z = 0; #10;
        w = 0; x = 1; y = 0; z = 1; #10;
        w = 0; x = 1; y = 1; z = 0; #10;
        w = 0; x = 1; y = 1; z = 1; #10;
        w = 1; x = 0; y = 0; z = 0; #10;
        w = 1; x = 0; y = 0; z = 1; #10;
        w = 1; x = 0; y = 1; z = 0; #10;
        w = 1; x = 0; y = 1; z = 1; #10;
        w = 1; x = 1; y = 0; z = 0; #10;
        w = 1; x = 1; y = 0; z = 1; #10;
        w = 1; x = 1; y = 1; z = 0; #10;
        w = 1; x = 1; y = 1; z = 1; #10;
    end
    initial #200 $finish;

endmodule

Class Problem/Lab Day 01/HW-Problem/Nand-Implementation/NAND.vcd
$date
	Sat Sep 21 08:36:00 2024
$end
$version
	Icarus Verilog
$end
$timescale
	1s
$end
$scope module test_NAND $end
$var wire 1 ! F $end
$var reg 1 " w $end
$var reg 1 # x $end
$var reg 1 $ y $end
$var reg 1 % z $end
$scope module uut $end
$var wire 1 ! F $end
$var wire 1 " w $end
$var wire 1 & w1 $end
$var wire 1 ' w2 $end
$var wire 1 ( w3 $end
$var wire 1 ) w4 $end
$var wire 1 * w5 $end
$var wire 1 + w_not $end
$var wire 1 # x $end
$var wire 1 , x_not $end
$var wire 1 $ y $end
$var wire 1 - y_not $end
$var wire 1 % z $end
$var wire 1 . z_not $end
$upscope $end
$upscope $end
$enddefinitions $end
#0
$dumpvars
1.
1-
1,
1+
0*
1)
0(
0'
1&
0%
0$
0#
0"
1!
$end
#10
0!
1*
0)
1'
1(
0.
1%
#20
1!
0*
1)
0'
1.
0-
0%
1$
#30
0!
1*
0)
1'
0.
1%
#40
0*
1)
1!
0'
0(
1.
1-
0,
0%
0$
1#
#50
0!
1*
0)
1'
1(
0.
1%
#60
1!
0*
1)
0'
1.
0-
0%
1$
#70
0!
1*
0)
1'
0.
1%
#80
0*
1!
1)
0(
0&
1.
1-
1,
0+
0%
0$
0#
1"
#90
1(
0.
1%
#100
1.
0-
0%
1$
#110
0.
1%
#120
1*
0)
0(
1&
1.
1-
0,
0%
0$
1#
#130
0!
1(
0.
1%
#140
1.
0-
0%
1$
#150
0.
1%
