Class Problem/anis-sir/Sequential/Moore/Moore_Model_Fig_5_20.sv
// State-diagram-based model (V2001, 2005)
module Moore_Model_Fig_5_20 (
output y_out,
input x_in, clock, reset
);
reg [1: 0] state;
parameter S0 = 2'b00, S1 = 2'b01, S2 = 2'b10, S3 = 2'b11;
always @ ( posedge clock, negedge reset)
 if (reset == 0) state <= S0; // Initialize to state S0
else case (state)
 S0: if (x_in) state <= S1; else state <= S0;
 S1: if (x_in) state <= S2; else state <= S1;
 S2: if (x_in) state <= S3; else state <= S2;
 S3: if (x_in) state <= S0; else state <= S3;
endcase
assign y_out = (state == S3); // Output of fl ip-fl ops
endmodule

Class Problem/anis-sir/Sequential/Moore/t_Moore_Model_Fig_5_20.sv
`include "Moore_Model_Fig_5_20.sv"
module t_Moore_Model_Fig_5_20;
	wire t_y_out;
	reg t_x_in, t_clock, t_reset;
	Moore_Model_Fig_5_20 M0 (t_y_out, t_x_in, t_clock, t_reset);
	initial 
		begin
		   $dumpfile("t_Moore_Model_Fig_5_20.vcd");
	       $dumpvars(0, t_Moore_Model_Fig_5_20);
		end
	initial #200 $finish;
	initial begin t_clock = 0; forever #5 t_clock = ~t_clock; end
	initial fork    
	 t_reset = 0;
	 #2 t_reset = 1;
	 #87 t_reset = 0;
	 #89 t_reset = 1;
	 
	 #10 t_x_in = 1;
	 #30 t_x_in = 0;
	 #40 t_x_in = 1;
	 #50 t_x_in = 0;
	 #52 t_x_in = 1;
	 #54 t_x_in = 0;
	 #70 t_x_in = 1;
	 #80 t_x_in = 1;
	 #70 t_x_in = 0;
	 #90 t_x_in = 1;
	 #100 t_x_in = 0;
	 #120 t_x_in = 1;
	 #160 t_x_in = 0;
	 #170 t_x_in = 1;
   join
endmodule

Class Problem/anis-sir/Sequential/Moore/t_Moore_Model_Fig_5_20.vcd
$date
	Mon Jul 08 13:27:42 2024
$end
$version
	Icarus Verilog
$end
$timescale
	1s
$end
$scope module t_Moore_Model_Fig_5_20 $end
$var wire 1 ! t_y_out $end
$var reg 1 " t_clock $end
$var reg 1 # t_reset $end
$var reg 1 $ t_x_in $end
$scope module M0 $end
$var wire 1 " clock $end
$var wire 1 # reset $end
$var wire 1 $ x_in $end
$var wire 1 ! y_out $end
$var parameter 2 % S0 $end
$var parameter 2 & S1 $end
$var parameter 2 ' S2 $end
$var parameter 2 ( S3 $end
$var reg 2 ) state [1:0] $end
$upscope $end
$upscope $end
$enddefinitions $end
$comment Show the parameter values. $end
$dumpall
b11 (
b10 '
b1 &
b0 %
$end
#0
$dumpvars
b0 )
x$
0#
0"
0!
$end
#2
1#
#5
1"
#10
0"
1$
#15
b1 )
1"
#20
0"
#25
b10 )
1"
#30
0"
0$
#35
1"
#40
0"
1$
#45
1!
b11 )
1"
#50
0"
0$
#52
1$
#54
0$
#55
1"
#60
0"
#65
1"
#70
0"
1$
#75
0!
b0 )
1"
#80
0"
#85
b1 )
1"
#87
b0 )
0#
#89
1#
#90
0"
#95
b1 )
1"
#100
0"
0$
#105
1"
#110
0"
#115
1"
#120
0"
1$
#125
b10 )
1"
#130
0"
#135
1!
b11 )
1"
#140
0"
#145
0!
b0 )
1"
#150
0"
#155
b1 )
1"
#160
0"
0$
#165
1"
#170
0"
1$
#175
b10 )
1"
#180
0"
#185
1!
b11 )
1"
#190
0"
#195
0!
b0 )
1"
