Class Problem/anis-sir/Sequential/Moore/Moore_Model_STR_Fig_5_20.sv
// Structural model
module Moore_Model_STR_Fig_5_20 (
	output y_out, A, B,
	input x_in, clock, reset);
	wire TA, TB;
	// Flip-fl op input equations
	assign TA = x_in & B;
	assign TB = x_in;
	// Output equation
	assign y_out = A & B;
	// Instantiate Toggle fl ip-fl ops
	 Toggle_flip_flop M_A (A, TA, clock, reset);
	 Toggle_flip_flop M_B (B, TB, clock, reset);
endmodule
          
module Toggle_flip_flop (Q, T, CLK, RST_b);
	output Q;
	input T, CLK, RST_b;
	reg Q;
	always @ ( posedge CLK, negedge RST_b)
	 if (RST_b == 0)
	    Q <= 1'b0;
	 else if (T)   // alternative else Q <= Q ^ T 
	    Q <= ~Q; 
endmodule

Class Problem/anis-sir/Sequential/Moore/Moore_Model_Fig_5_20.sv
// State-diagram-based model (V2001, 2005)
module Moore_Model_Fig_5_20 (
output y_out,
input x_in, clock, reset
);
reg [1: 0] state;
parameter S0 = 2'b00, S1 = 2'b01, S2 = 2'b10, S3 = 2'b11;
always @ ( posedge clock, negedge reset)
 if (reset == 0) state <= S0; // Initialize to state S0
else case (state)
 S0: if (x_in) state <= S1; else state <= S0;
 S1: if (x_in) state <= S2; else state <= S1;
 S2: if (x_in) state <= S3; else state <= S2;
 S3: if (x_in) state <= S0; else state <= S3;
endcase
assign y_out = (state == S3); // Output of fl ip-fl ops
endmodule

Class Problem/anis-sir/Sequential/Moore/t_Moore_Model_STR_Fig_5_20.sv
`include "Moore_Model_STR_Fig_5_20.sv"
`include "Moore_Model_Fig_5_20.sv"
module t_Moore_Model_STR_Fig_5_20;
	wire t_y_out_1;
	wire t_y_out_2;
 	reg t_x_in, t_clock, t_reset;
	Moore_Model_Fig_5_20 M1 (t_y_out_1, t_x_in, t_clock, t_reset);
	Moore_Model_STR_Fig_5_20 M2 (t_y_out_2, A, B, t_x_in, t_clock, t_reset);
	initial 
		begin
		   $dumpfile("t_Moore_Model_STR_Fig_5_20.vcd");
	       $dumpvars(0, t_Moore_Model_STR_Fig_5_20);
		end
	initial #100 $finish;
	initial 
	  begin 
	  	  t_reset = 0;
	      t_clock = 0;
	      #5 t_reset = 1;
	      repeat (16)
	        #5 t_clock = ~t_clock; 
      end
	initial 
	 begin
 		t_x_in = 0;
		#15 t_x_in = 1;
		repeat (8)
		   #10 t_x_in = ~t_x_in;
	end
endmodule

Class Problem/anis-sir/Sequential/Moore/t_Moore_Model_STR_Fig_5_20.vcd
$date
	Mon Jul 08 13:35:26 2024
$end
$version
	Icarus Verilog
$end
$timescale
	1s
$end
$scope module t_Moore_Model_STR_Fig_5_20 $end
$var wire 1 ! t_y_out_2 $end
$var wire 1 " t_y_out_1 $end
$var wire 1 # B $end
$var wire 1 $ A $end
$var reg 1 % t_clock $end
$var reg 1 & t_reset $end
$var reg 1 ' t_x_in $end
$scope module M1 $end
$var wire 1 % clock $end
$var wire 1 & reset $end
$var wire 1 ' x_in $end
$var wire 1 " y_out $end
$var parameter 2 ( S0 $end
$var parameter 2 ) S1 $end
$var parameter 2 * S2 $end
$var parameter 2 + S3 $end
$var reg 2 , state [1:0] $end
$upscope $end
$scope module M2 $end
$var wire 1 - TA $end
$var wire 1 . TB $end
$var wire 1 % clock $end
$var wire 1 & reset $end
$var wire 1 ' x_in $end
$var wire 1 ! y_out $end
$var wire 1 # B $end
$var wire 1 $ A $end
$scope module M_A $end
$var wire 1 % CLK $end
$var wire 1 & RST_b $end
$var wire 1 - T $end
$var reg 1 $ Q $end
$upscope $end
$scope module M_B $end
$var wire 1 % CLK $end
$var wire 1 & RST_b $end
$var wire 1 . T $end
$var reg 1 # Q $end
$upscope $end
$upscope $end
$upscope $end
$enddefinitions $end
$comment Show the parameter values. $end
$dumpall
b11 +
b10 *
b1 )
b0 (
$end
#0
$dumpvars
0.
0-
b0 ,
0'
0&
0%
0$
0#
0"
0!
$end
#5
1&
#10
1%
#15
0%
1.
1'
#20
1-
b1 ,
1#
1%
#25
0-
0%
0.
0'
#30
1%
#35
1-
0%
1.
1'
#40
0-
b10 ,
1$
0#
1%
#45
0%
0.
0'
#50
1%
#55
0%
1.
1'
#60
1!
1-
1"
b11 ,
1#
1%
#65
0-
0%
0.
0'
#70
1%
#75
1-
0%
1.
1'
#80
0!
0-
0"
b0 ,
0$
0#
1%
#85
0%
0.
0'
#95
1.
1'
